clientes_inadimplentes/__init__.py
clientes_inadimplentes/clientes_inadimplentes.py
clientes_inadimplentes-0.0.1.dist-info/METADATA
clientes_inadimplentes-0.0.1.dist-info/WHEEL
clientes_inadimplentes-0.0.1.dist-info/top_level.txt
clientes_inadimplentes-0.0.1.dist-info/RECORD
