Metadata-Version: 2.1
Name: clientes-inadimplentes
Version: 0.0.1
Summary: Criar função para descobrir os clientes inadimplentes de uma empresa
Home-page: https://github.com/ArturJBraga/clientes_inadimplentes.git
Author: ArturJBraga
Author-email: mr.arturj@gmail.com
License: UNKNOWN
Platform: UNKNOWN
Requires-Python: >=3.5
